[
    {
        "date": "< Jun 58 BCE",
        "title":  "Build up to Battle of Arar"
    },
    {
        "date": "Jun 58 BCE",
        "title": "Battle of Arar",
        "url": "http://en.wikipedia.org/wiki/Battle_of_the_Arar"
    },
    {
        "date": "Jul 58 BCE",
        "title": "Battle of Bribracte",
        "url": "http://en.wikipedia.org/wiki/Battle_of_Bibracte"
    },
    {
        "date": "Sep 58 BCE",
        "title": "Caesar defeats Ariovistus near Belfort"
    },
    {
        "date": "57 BCE",
        "title": "Battle of Axona",
        "url": "http://en.wikipedia.org/wiki/Battle_of_the_Axona"
    },
    {
        "date": "57 BCE",
        "title": "Battle of Sabis",
        "url": "http://en.wikipedia.org/wiki/Battle_of_the_Sabis"
    },
    {
        "date": "57 BCE",
        "title": "Battle of Octodurus",
        "url": "http://en.wikipedia.org/wiki/Battle_of_Octodurus"
    },
    {
        "date": "5 May 53 BCE",
        "title": "Battle of Carrhae",
        "url": "http://en.wikipedia.org/wiki/Battle_of_Carrhae"
    },
    {
        "date": "Sep 52 BCE",
        "title": "Battle of Alesia",
        "url": "http://en.wikipedia.org/wiki/Battle_of_Alesia"
    },
    {
        "date": "Jun 49 BCE",
        "title": "Battle of Ilerda",
        "url": "http://en.wikipedia.org/wiki/Battle_of_Ilerda"
    },
    {
        "date": "24 Aug 49 BCE",
        "title": "Battle of Bagradas River",
        "url": "http://en.wikipedia.org/wiki/Battle_of_the_Bagradas_River_(49_BC)"
    },
    {
        "date": "10 Jul 48 BCE",
        "title": "Battle of Dyrrhachium",
        "url": "http://en.wikipedia.org/wiki/Battle_of_Dyrrhachium_(48_BC)"
    },
    {
        "date": "9 Aug 48 BCE",
        "title": "Battle of Pharsalus",
        "url": "http://en.wikipedia.org/wiki/Battle_of_Pharsalus"
    },
    {
        "date": "Feb 47 BCE",
        "title": "Battle of the Nile",
        "url": "http://en.wikipedia.org/wiki/Battle_of_the_Nile_(47_BC)"
    },
    {
        "date": "2 Aug 47 BCE",
        "title": "Battle of Zela",
        "url": "http://en.wikipedia.org/wiki/Battle_of_Zela"
    },
    {
        "date": "4 Jan 46 BCE",
        "title": "Battle of Ruspina",
        "url": "http://en.wikipedia.org/wiki/Battle_of_Ruspina"
    },
    {
        "date": "6 Apr 46 BCE",
        "title": "Battle of Thapsus",
        "url": "http://en.wikipedia.org/wiki/Battle_of_Thapsus"
    },
    {
        "date": "17 Mar 45 BCE",
        "title": "Battle of Munda",
        "url": "http://en.wikipedia.org/wiki/Battle_of_Munda"
    },
    {
        "date": "14 Apr 43 BCE",
        "title": "Battle of Forum Gallorum",
        "url": "http://en.wikipedia.org/wiki/Battle_of_Forum_Gallorum"
    },
    {
        "date": "21 Apr 43 BCE",
        "title": "Battle of Mutina",
        "url": "http://en.wikipedia.org/wiki/Battle_of_Mutina"
    },
    {
        "date": "3 Oct 42 BCE",
        "title": "First Battle of Philippi",
        "url": "http://en.wikipedia.org/wiki/Battle_of_Philippi"
    },
    {
        "date": "23 Oct 42 BCE",
        "title": "Second Battle of Philippi",
        "url": "http://en.wikipedia.org/wiki/Battle_of_Philippi"
    },
    {
        "date": "40 BCE",
        "title": "Battle of Perugia",
        "url": "http://en.wikipedia.org/wiki/Battle_of_Perugia"
    },
    {
        "date": "3 Sep 36 BCE",
        "title": "Battle of Naulochus",
        "url": "http://en.wikipedia.org/wiki/Battle_of_Naulochus"
    },
    {
        "date": "2 Sep 31 BCE",
        "title": "Battle of Actium",
        "url": "http://en.wikipedia.org/wiki/Battle_of_Actium"
    },
    {
        "date": "25 BCE",
        "title": "Battle of Velica",
        "url": "http://en.wikipedia.org/wiki/Battle_of_Vellica"
    },
    {
        "date": "25 BCE",
        "title": "Siege of Aracillum",
        "url": "http://en.wikipedia.org/wiki/Siege_of_Aracillum_(25_BC)"
    },
    {
        "date": "16 BCE",
        "title": "Clades Lolliana",
        "url": "http://en.wikipedia.org/wiki/Clades_Lolliana"
    },
    {
        "date": "11 BCE",
        "title": "Battle of Lupia River",
        "url": "http://en.wikipedia.org/wiki/Battle_of_the_Lupia_River"
    },
    {
        "date": "Sep 9 CE",
        "title": "Battle of Teutoburg Forest",
        "url": "http://en.wikipedia.org/wiki/Battle_of_the_Teutoburg_Forest"
    },
    {
        "date": "16 CE",
        "title": "Battle of the Weser River",
        "url": "http://en.wikipedia.org/wiki/Battle_of_the_Weser_River"
    },
    {
        "date": "43 CE",
        "title": "Battle of the Medway",
        "url": "http://en.wikipedia.org/wiki/Battle_of_the_Medway"
    },
    {
        "date": "49 CE",
        "title": "Siege of Uspe"
    },
    {
        "date": "50 CE",
        "title": "Battle of Caer Caradoc",
        "url": "http://en.wikipedia.org/wiki/Battle_of_Caer_Caradoc"
    },
    {
        "date": "58 CE",
        "title": "Sack of Artaxata"
    },
    {
        "date": "59 CE",
        "title": "Capture of Tigranocerta"
    },
    {
        "date": "60 CE",
        "title": "Battle of Camulodunum",
        "url": "http://en.wikipedia.org/wiki/Battle_of_Camulodunum"
    },
    {
        "date": "61 CE",
        "title": "Battle of Watling Street",
        "url": "http://en.wikipedia.org/wiki/Battle_of_Watling_Street"
    },
    {
        "date": "62 CE",
        "title": "Battle of Rhandeia",
        "url": "http://en.wikipedia.org/wiki/Roman%E2%80%93Parthian_War_of_58%E2%80%9363#Battle_of_Rhandeia"
    },
    {
        "date": "66 CE",
        "title": "Battle of Beth-Horon",
        "url": "http://en.wikipedia.org/wiki/Battle_of_Beth_Horon_(66)"
    },
    {
        "date": "69 CE",
        "title": "Battle of Forum Julii",
        "url": "http://en.wikipedia.org/wiki/Battle_of_Forum_Julii"
    },
    {
        "date": "14 Apr 69 CE",
        "title": "First battle of Bedriacum",
        "url": "http://en.wikipedia.org/wiki/Battle_of_Bedriacum"
    },
    {
        "date": "24 Oct 69 CE",
        "title": "Second battle of Bedriacum",
        "url": "http://en.wikipedia.org/wiki/Battle_of_Bedriacum#Second_Battle_of_Bedriacum"
    },
    {
        "date": "71 CE",
        "title": "Battle of Scotch Corner",
        "url": "http://en.wikipedia.org/wiki/Battle_of_Scotch_Corner"
    },
    {
        "date": "73 CE",
        "title": "Siege of Masada",
        "url": "http://en.wikipedia.org/wiki/Siege_of_Masada"
    },
    {
        "date": "84 CE",
        "title": "Battle of Mons Graupius",
        "url": "http://en.wikipedia.org/wiki/Battle_of_Mons_Graupius"
    },
    {
        "date": "> 84 CE",
        "title": "Aftermath of Battle of Mons Graupius"
    }
]